<xml xmlns="http://www.w3.org/1999/xhtml"><variables><variable type="" id="8hQL(#[*X%k}!gp!HgHB">value</variable></variables><block type="variables_set" id="=tG)-.qpzJZm-:pTaP.r" x="188" y="213"><field name="VAR" id="8hQL(#[*X%k}!gp!HgHB" variabletype="">value</field><value name="VALUE"><block type="io_analog_read" id="8$9AR#Ai6p_sbBB50bB?"><value name="PIN"><shadow type="pins_analog" id=";y_T.]NdZR6{-Xqk:c19"><field name="PIN">A0</field></shadow></value></block></value><next><block type="serial_print" id="^%VZiY?-d)Z;qrrFK{_u"><field name="serial_select">Serial</field><value name="CONTENT"><block type="text" id="71Bl;TkZTJJfF7^[lC|-"><field name="TEXT">Value =  </field></block></value><next><block type="serial_println" id="p-*^~P6v@WRb~~D:Msp:"><field name="serial_select">Serial</field><value name="CONTENT"><block type="variables_get" id="{B*#GerVYL+EfCtSmdIX"><field name="VAR" id="8hQL(#[*X%k}!gp!HgHB" variabletype="">value</field></block></value><next><block type="base_delay" id="3aymh{?}G**6LP-cC`08"><field name="UNIT">delay</field><value name="DELAY_TIME"><shadow type="math_number" id="mbQcB|]d2v_Ao.v34X?G"><field name="NUM">500</field></shadow></value></block></next></block></next></block></next></block></xml>